{
  "device": "cuda",
  "ended_at_utc": "2026-07-19T14:07:34.252682+00:00",
  "evaluation_iccd_raw_read": false,
  "experiment_id": "e4_g_cg_multiseed_gate_revision_20260719_seed_20260720",
  "experiments": [
    "G",
    "CG_NC"
  ],
  "final_status": "TRAINING-RUN-VALID-WITH-LIMITATIONS",
  "git_commit": "586cfdb8fffbb9b2a74fb3bf2b0142d426ebdbd1",
  "smoke": false,
  "source_data_protected": true,
  "started_at_utc": "2026-07-19T14:02:41.124041+00:00",
  "training_info": {
    "CG_NC": {
      "best_epoch": 22,
      "best_validation_l1": 0.001165929092711204,
      "best_validation_psnr": 57.39310409676315,
      "elapsed_seconds": 123.86262670002179,
      "parameter_count": 481745,
      "peak_gpu_bytes": 271566848
    },
    "G": {
      "best_epoch": 17,
      "best_validation_l1": 0.0011808673212400232,
      "best_validation_psnr": 57.27963664389064,
      "elapsed_seconds": 123.83070200000657,
      "parameter_count": 481745,
      "peak_gpu_bytes": 265765376
    }
  }
}
